electrum_fp/__init__.py
electrum_fp/electrum.py
electrum_fp-0.1.1.dist-info/licenses/LICENSE
electrum_fp-0.1.1.dist-info/METADATA
electrum_fp-0.1.1.dist-info/WHEEL
electrum_fp-0.1.1.dist-info/top_level.txt
electrum_fp-0.1.1.dist-info/RECORD
