Metadata-Version: 2.4
Name: electrum-fp
Version: 0.1.1
Summary: Metal-aware molecular fingerprinting tools
Author: Markus Orsi
Author-email: markus.orsi@unibe.ch
Keywords: cheminformatics,fingerprint,electrum,coordination
Classifier: Programming Language :: Python :: 3
Classifier: License :: OSI Approved :: MIT License
Classifier: Operating System :: OS Independent
Requires-Python: >=3.7
License-File: LICENSE
Requires-Dist: numpy
Requires-Dist: pandas
Requires-Dist: rdkit
Dynamic: author
Dynamic: author-email
Dynamic: classifier
Dynamic: description
Dynamic: description-content-type
Dynamic: keywords
Dynamic: license-file
Dynamic: requires-dist
Dynamic: requires-python
Dynamic: summary
